cfn_perm-0.1.3.dist-info/licenses/LICENSE
source/__init__.py
source/app.py
cfn_perm-0.1.3.dist-info/METADATA
cfn_perm-0.1.3.dist-info/WHEEL
cfn_perm-0.1.3.dist-info/entry_points.txt
cfn_perm-0.1.3.dist-info/top_level.txt
cfn_perm-0.1.3.dist-info/RECORD
