Metadata-Version: 2.4
Name: cfn-perm
Version: 0.1.3
Summary: A tool to automatically generate IAM permissions from CloudFormation templates
Home-page: https://github.com/mrlikl/cfn-perm.git
Author: S Murali Krishnan
Author-email: S Murali Krishnan <mrlikrsh@gmail.com>
Project-URL: Homepage, https://github.com/mrlikl/cfn-perm.git
Keywords: aws, cloudformation, iam, permissions
Classifier: Programming Language :: Python :: 3
Classifier: Operating System :: OS Independent
Classifier: Topic :: Utilities
Requires-Python: >=3.9
License-File: LICENSE
Requires-Dist: boto3
Requires-Dist: pyyaml
Dynamic: author
Dynamic: home-page
Dynamic: license-file
Dynamic: requires-python
